{"fechaNacimiento":Sat Dec 02 00:00:00 COT 2073,"peso":113.02428755494824,"cedula":"1723713482","direccion":"Calle Principal, Loja","ocupacion":"Abogado","estadoCivil":"Viudo","colorPelo":"Rubio","nombre":"Laura","edad":80,"pais":"Ecuador","nacionalidad":null,"ciudadNacimiento":"Cuenca","colorOjos":"Azul","grupoSanguineo":"B-","altura":1.847901409304909,"hobbies":"Cocinar, Viajar, Cocinar, Viajar","apellido":"García","genero":"Masculino","telefono":"+593-395357306","email":"maría.díaz@example.com"}