{"fechaNacimiento":Sun Oct 21 00:00:00 COT 2063,"peso":116.04030896600575,"cedula":"1700409416","direccion":"Callejon Secundario, Manta","ocupacion":"Profesor","estadoCivil":"Divorciado","colorPelo":"Pelirrojo","nombre":"Ana","edad":93,"pais":"Ecuador","nacionalidad":null,"ciudadNacimiento":"Loja","colorOjos":"Negro","grupoSanguineo":"AB+","altura":1.653977469181193,"hobbies":"Deportes, Deportes, Viajar","apellido":"López","genero":"Femenino","telefono":"+593-711776564","email":"juan.garcía@example.com"}