{"fechaNacimiento":Mon Jul 23 00:00:00 COT 2063,"peso":82.85346422420872,"cedula":"1710668008","direccion":"Avenida Central, Quito","ocupacion":"Doctor","estadoCivil":"Soltero","colorPelo":"Pelirrojo","nombre":"Juan","edad":68,"pais":"Ecuador","nacionalidad":null,"ciudadNacimiento":"Manta","colorOjos":"Negro","grupoSanguineo":"AB+","altura":1.5084633182825933,"hobbies":"Deportes, Deportes, Deportes, Pintar","apellido":"Gómez","genero":"Femenino","telefono":"+593-998886536","email":"pedro.pérez@example.com"}