{"fechaNacimiento":Fri Mar 27 00:00:00 COT 2065,"peso":91.5649261867656,"cedula":"1716982521","direccion":"Avenida Central, Guayaquil","ocupacion":"Doctor","estadoCivil":"Divorciado","colorPelo":"Pelirrojo","nombre":"Carlos","edad":45,"pais":"Ecuador","nacionalidad":null,"ciudadNacimiento":"Quito","colorOjos":"Marrón","grupoSanguineo":"B+","altura":1.9851866142132741,"hobbies":"Pintar, Viajar","apellido":"Martínez","genero":"Masculino","telefono":"+593-035573472","email":"ana.martínez@example.com"}